google/cloud/cloudcontrolspartner/__init__.py
google/cloud/cloudcontrolspartner/gapic_version.py
google/cloud/cloudcontrolspartner/py.typed
google/cloud/cloudcontrolspartner_v1/__init__.py
google/cloud/cloudcontrolspartner_v1/gapic_metadata.json
google/cloud/cloudcontrolspartner_v1/gapic_version.py
google/cloud/cloudcontrolspartner_v1/py.typed
google/cloud/cloudcontrolspartner_v1/services/__init__.py
google/cloud/cloudcontrolspartner_v1/services/cloud_controls_partner_core/__init__.py
google/cloud/cloudcontrolspartner_v1/services/cloud_controls_partner_core/async_client.py
google/cloud/cloudcontrolspartner_v1/services/cloud_controls_partner_core/client.py
google/cloud/cloudcontrolspartner_v1/services/cloud_controls_partner_core/pagers.py
google/cloud/cloudcontrolspartner_v1/services/cloud_controls_partner_core/transports/__init__.py
google/cloud/cloudcontrolspartner_v1/services/cloud_controls_partner_core/transports/base.py
google/cloud/cloudcontrolspartner_v1/services/cloud_controls_partner_core/transports/grpc.py
google/cloud/cloudcontrolspartner_v1/services/cloud_controls_partner_core/transports/grpc_asyncio.py
google/cloud/cloudcontrolspartner_v1/services/cloud_controls_partner_core/transports/rest.py
google/cloud/cloudcontrolspartner_v1/services/cloud_controls_partner_core/transports/rest_base.py
google/cloud/cloudcontrolspartner_v1/services/cloud_controls_partner_monitoring/__init__.py
google/cloud/cloudcontrolspartner_v1/services/cloud_controls_partner_monitoring/async_client.py
google/cloud/cloudcontrolspartner_v1/services/cloud_controls_partner_monitoring/client.py
google/cloud/cloudcontrolspartner_v1/services/cloud_controls_partner_monitoring/pagers.py
google/cloud/cloudcontrolspartner_v1/services/cloud_controls_partner_monitoring/transports/__init__.py
google/cloud/cloudcontrolspartner_v1/services/cloud_controls_partner_monitoring/transports/base.py
google/cloud/cloudcontrolspartner_v1/services/cloud_controls_partner_monitoring/transports/grpc.py
google_cloud_cloudcontrolspartner-0.4.0.dist-info/licenses/LICENSE
google_cloud_cloudcontrolspartner-0.4.0.dist-info/METADATA
google_cloud_cloudcontrolspartner-0.4.0.dist-info/WHEEL
google_cloud_cloudcontrolspartner-0.4.0.dist-info/top_level.txt
google_cloud_cloudcontrolspartner-0.4.0.dist-info/RECORD
